README.rst
setup.py
src/sentry_riemann/__init__.py
src/sentry_riemann/forms.py
src/sentry_riemann/plugin.py
src/sentry_riemann.egg-info/PKG-INFO
src/sentry_riemann.egg-info/SOURCES.txt
src/sentry_riemann.egg-info/dependency_links.txt
src/sentry_riemann.egg-info/entry_points.txt
src/sentry_riemann.egg-info/not-zip-safe
src/sentry_riemann.egg-info/pbr.json
src/sentry_riemann.egg-info/requires.txt
src/sentry_riemann.egg-info/top_level.txt