Metadata-Version: 1.1
Name: sentry-riemann
Version: 0.0.4
Summary: A Sentry extension which send errors stats to Riemann
Home-page: http://github.com/timbuchwaldt/sentry-riemann
Author: Tim Buchwaldt
Author-email: tim@buchwaldt.ws
License: MIT
Keywords: sentry riemann
Platform: UNKNOWN
Classifier: Intended Audience :: Developers
Classifier: Intended Audience :: System Administrators
Classifier: Operating System :: OS Independent
Classifier: Programming Language :: Python
Classifier: Framework :: Django
Classifier: Topic :: Software Development
